plotly_dash_ketcher/923.plotly_dash_ketcher.js
plotly_dash_ketcher/PlotlyDashKetcher.py
plotly_dash_ketcher/__init__.py
plotly_dash_ketcher/_imports_.py
plotly_dash_ketcher/metadata.json
plotly_dash_ketcher/package-info.json
plotly_dash_ketcher/plotly_dash_ketcher.js
plotly_dash_ketcher-1.0.0.dist-info/LICENSE
plotly_dash_ketcher-1.0.0.dist-info/METADATA
plotly_dash_ketcher-1.0.0.dist-info/WHEEL
plotly_dash_ketcher-1.0.0.dist-info/top_level.txt
plotly_dash_ketcher-1.0.0.dist-info/RECORD
