Metadata-Version: 2.1
Name: plotly-dash-ketcher
Version: 1.0.0
Summary: A wrapper for EPAM's ketcher
Author: Jonathan Bisson <bjonnh-npm@bjonnh.net>
License: MIT
Classifier: Framework :: Dash
License-File: LICENSE
